Metadata-Version: 2.4
Name: rapyuta-io-cli
Version: 9.13.4
Summary: rapyuta.io Command Line Interface
Author-email: Rapyuta Robotics <opensource@rapyuta-robotics.com>
License:                                  Apache License
Project-URL: Homepage, https://cli.rapyuta.io
Project-URL: Documentation, https://cli.rapyuta.io/
Project-URL: Repository, https://github.com/rapyuta-robotics/rapyuta-io-cli.git
Project-URL: Issues, https://github.com/rapyuta-robotics/rapyuta-io-cli/issues
Project-URL: Changelog, https://github.com/rapyuta-robotics/rapyuta-io-cli/blob/main/CHANGELOG.md
Classifier: Programming Language :: Python
Classifier: Programming Language :: Python :: 3.8
Classifier: Programming Language :: Python :: 3.9
Classifier: Programming Language :: Python :: 3.10
Classifier: Programming Language :: Python :: 3.11
Classifier: Programming Language :: Python :: 3.12
Classifier: Programming Language :: Python :: 3.13
Requires-Python: >=3.8.10
License-File: LICENSE
Requires-Dist: argparse>=1.4.0
Requires-Dist: click-completion>=0.5.2
Requires-Dist: click-help-colors>=0.9.1
Requires-Dist: click-repl>=0.2.0
Requires-Dist: click-spinner>=0.1.10
Requires-Dist: click!=8.2.0,>=8.1.8
Requires-Dist: dictdiffer>=0.9.0
Requires-Dist: directory-tree>=0.0.3.1
Requires-Dist: email-validator==2.0.0.post2
Requires-Dist: etcd3gw>=2.4.0
Requires-Dist: graphlib-backport>=1.0.3
Requires-Dist: graphviz>=0.20.3
Requires-Dist: jinja2>=3.0.1
Requires-Dist: jsonschema==4.23.0
Requires-Dist: munch>=2.4.0
Requires-Dist: pretty-traceback>=2022.1018
Requires-Dist: pyrfc3339>=1.1
Requires-Dist: python-benedict>=0.33.2
Requires-Dist: python-dateutil>=2.8.2
Requires-Dist: python-hosts>=1.0.7
Requires-Dist: python-magic>=0.4.27; os_name != "nt"
Requires-Dist: python-magic-bin>=0.4.14; os_name == "nt"
Requires-Dist: pytz
Requires-Dist: pyyaml>=5.4.1
Requires-Dist: rapyuta_io>=3.0.0
Requires-Dist: requests>=2.20.0
Requires-Dist: semver>=3.0.0
Requires-Dist: setuptools
Requires-Dist: six>=1.13.0
Requires-Dist: tabulate>=0.8.0
Requires-Dist: urllib3>=1.23
Requires-Dist: waiting>=1.4.1
Requires-Dist: yaspin==2.5.0
Requires-Dist: ansible-core>=2.13.13
Dynamic: license-file
